LICENSE
http_exceptions/__init__.py
http_exceptions/client_exceptions.py
http_exceptions/http_exception.py
http_exceptions/py.typed
http_exceptions/server_exceptions.py
http_exceptions-0.2.9.dist-info/LICENSE
http_exceptions-0.2.9.dist-info/WHEEL
http_exceptions-0.2.9.dist-info/METADATA
http_exceptions-0.2.9.dist-info/RECORD
